wrangalytics/__init__.py
wrangalytics-0.0.2.dev0.dist-info/METADATA
wrangalytics-0.0.2.dev0.dist-info/RECORD
wrangalytics-0.0.2.dev0.dist-info/WHEEL
wrangalytics-0.0.2.dev0.dist-info/top_level.txt
wranglyzer/__init__.py
