Metadata-Version: 2.1
Name: wrangalytics
Version: 0.0.2.dev0
Summary: A python package for routine data wrangling and analytics tasks
Home-page: https://github.com/acastrounis/wrangalytics
Author: Alex Castrounis
Author-email: dev@innoarchitech.com
License: MIT
Platform: UNKNOWN
Classifier: Programming Language :: Python :: 3
Classifier: License :: OSI Approved :: MIT License
Classifier: Operating System :: OS Independent
Requires-Python: >=3.6.*
